xj_recycle/__init__.py
xj_recycle/admin.py
xj_recycle/apps.py
xj_recycle/models.py
xj_recycle/tool.py
xj_recycle/urls.py
xj_recycle/apis/__init__.py
xj_recycle/apis/recycle_bin_add.py
xj_recycle/apis/recycle_bin_list.py
xj_recycle/apis/recycle_bin_restore.py
xj_recycle/services/__init__.py
xj_recycle/services/recycle_service.py
xj_recycle-1.0.5.dist-info/METADATA
xj_recycle-1.0.5.dist-info/PKG-INFO~12c86d998be384ef2e8ad65713880f88b1070905
xj_recycle-1.0.5.dist-info/WHEEL
xj_recycle-1.0.5.dist-info/top_level.txt
xj_recycle-1.0.5.dist-info/RECORD
